src/__init__.py
src/main.py
ConnectWifiWithPy-0.0.1.0.dist-info/LICENSE
ConnectWifiWithPy-0.0.1.0.dist-info/METADATA
ConnectWifiWithPy-0.0.1.0.dist-info/WHEEL
ConnectWifiWithPy-0.0.1.0.dist-info/top_level.txt
ConnectWifiWithPy-0.0.1.0.dist-info/RECORD
