Metadata-Version: 2.1
Name: ConnectWifiWithPy
Version: 0.0.1.0
Summary: Create, Edit and Change Infomation of XML File
Home-page: https://github.com/nguyentranphucbao/ConnectWifiWithPython
Author: @KudoKuro
Author-email: nguyentranphucbao@gmail.com
License: UNKNOWN
Platform: UNKNOWN
Classifier: Programming Language :: Python :: 3
Classifier: License :: OSI Approved :: MIT License
Classifier: Operating System :: OS Independent
Requires-Python: >=3.5
